synapse/__init__.py
synapse/a2a_client.py
synapse/a2a_compat.py
synapse/approval.py
synapse/auth.py
synapse/cli.py
synapse/config.py
synapse/controller.py
synapse/delegation.py
synapse/error_detector.py
synapse/file_safety.py
synapse/grpc_server.py
synapse/history.py
synapse/logging_config.py
synapse/output_parser.py
synapse/port_manager.py
synapse/registry.py
synapse/reply_stack.py
synapse/server.py
synapse/settings.py
synapse/shell.py
synapse/shell_hook.py
synapse/startup_tui.py
synapse/status.py
synapse/terminal_jump.py
synapse/utils.py
synapse/webhooks.py
synapse/commands/__init__.py
synapse/commands/config.py
synapse/commands/instructions.py
synapse/commands/list.py
synapse/commands/start.py
synapse/commands/renderers/__init__.py
synapse/commands/renderers/rich_renderer.py
synapse/profiles/claude.yaml
synapse/profiles/codex.yaml
synapse/profiles/copilot.yaml
synapse/profiles/dummy.yaml
synapse/profiles/gemini.yaml
synapse/profiles/opencode.yaml
synapse/proto/__init__.py
synapse/proto/a2a_pb2.py
synapse/proto/a2a_pb2_grpc.py
synapse/templates/.synapse/default.md
synapse/templates/.synapse/delegate.md
synapse/templates/.synapse/file-safety.md
synapse/templates/.synapse/gemini.md
synapse/templates/.synapse/settings.json
synapse/tools/a2a.py
synapse_a2a-0.3.15.dist-info/METADATA
synapse_a2a-0.3.15.dist-info/WHEEL
synapse_a2a-0.3.15.dist-info/entry_points.txt
synapse_a2a-0.3.15.dist-info/top_level.txt
synapse_a2a-0.3.15.dist-info/RECORD
