Metadata-Version: 2.4
Name: synapse-a2a
Version: 0.3.15
Summary: Agent-to-Agent communication protocol for CLI agents
Author: Synapse A2A Team
License: MIT
Requires-Python: >=3.10
Requires-Dist: fastapi>=0.100.0
Requires-Dist: uvicorn>=0.23.0
Requires-Dist: pyyaml>=6.0
Requires-Dist: requests>=2.31.0
Requires-Dist: httpx>=0.24.0
Requires-Dist: questionary>=2.0.0
Requires-Dist: rich>=13.0.0
Requires-Dist: simple-term-menu>=1.6.6
Requires-Dist: watchdog>=3.0.0
Requires-Dist: pyperclip>=1.8.0
